futuraAiToolbox/__init__.py
futuraAiToolbox/futuraAiToolbox.py
futuraAiToolbox/futuraAiUtils.py
futuraAiToolbox/guiBackends/__init__.py
futuraAiToolbox/guiBackends/bokehbackend.py
futuraAiToolbox/guiBackends/theme.yaml
futuraAiToolbox/guiBackends/tkbackend.py
futuraAiToolbox/quant/__init__.py
futuraAiToolbox/quant/stats.py
futuraAiToolbox-0.0.16.data/data/futuraAiToolbox/guiBackends/theme.yaml
futuraAiToolbox-0.0.16.dist-info/DESCRIPTION.rst
futuraAiToolbox-0.0.16.dist-info/METADATA
futuraAiToolbox-0.0.16.dist-info/RECORD
futuraAiToolbox-0.0.16.dist-info/WHEEL
futuraAiToolbox-0.0.16.dist-info/metadata.json
futuraAiToolbox-0.0.16.dist-info/top_level.txt
