Metadata-Version: 2.0
Name: futuraAiToolbox
Version: 0.0.16
Summary: Python based toolbox for futuraAi
Home-page: http://futura.ai
Author: Tanmay
Author-email: tanmay@futura.ai
License: MIT
Download-URL: https://gitlab.com/futura.ai/genesisrepo/repository/master/archive.zip
Platform: UNKNOWN
Requires-Dist: backports.functools-lru-cache (>=1.5)
Requires-Dist: cycler (>=0.10.0)
Requires-Dist: kiwisolver (>=1.0.1)
Requires-Dist: matplotlib (>=2.2.2)
Requires-Dist: numpy (>=1.14.2)
Requires-Dist: pandas (>=0.22.0)
Requires-Dist: pyparsing (>=2.2.0)
Requires-Dist: python-dateutil (>=2.7.2)
Requires-Dist: pytz (>=2018.3)
Requires-Dist: six (>=1.11.0)
Requires-Dist: subprocess32 (>=3.2.7)
Requires-Dist: bokeh (==0.12.15)
